<annotation>
	<folder>Dim_15</folder>
	<filename>032.bmp</filename>
	<path>D:\dataset\TargetSim54\result\Dim_15\032.bmp</path>
	<source>
		<database>Unknown</database>
	</source>
	<size>
		<width>256</width>
		<height>256</height>
		<depth>3</depth>
	</size>
	<segmented>0</segmented>
	<object>
		<name>Target</name>
		<pose>Unspecified</pose>
		<truncated>0</truncated>
		<difficult>0</difficult>
		<bndbox>
			<xmin>91</xmin>
			<ymin>65</ymin>
			<xmax>99</xmax>
			<ymax>72</ymax>
		</bndbox>
	</object>
</annotation>
