<annotation>
	<folder>Data9</folder>
	<filename>230.bmp</filename>
	<path>D:\dataset\DIYD_Data\Data9\230.bmp</path>
	<source>
		<database>Unknown</database>
	</source>
	<size>
		<width>256</width>
		<height>256</height>
		<depth>1</depth>
	</size>
	<segmented>0</segmented>
	<object>
		<name>Target</name>
		<pose>Unspecified</pose>
		<truncated>0</truncated>
		<difficult>0</difficult>
		<bndbox>
			<xmin>126</xmin>
			<ymin>102</ymin>
			<xmax>132</xmax>
			<ymax>108</ymax>
		</bndbox>
	</object>
</annotation>
