<annotation>
	<folder>Dim_22</folder>
	<filename>025.bmp</filename>
	<path>D:\dataset\TargetSim54\result\Dim_22\025.bmp</path>
	<source>
		<database>Unknown</database>
	</source>
	<size>
		<width>256</width>
		<height>256</height>
		<depth>3</depth>
	</size>
	<segmented>0</segmented>
	<object>
		<name>Target</name>
		<pose>Unspecified</pose>
		<truncated>0</truncated>
		<difficult>0</difficult>
		<bndbox>
			<xmin>50</xmin>
			<ymin>152</ymin>
			<xmax>63</xmax>
			<ymax>162</ymax>
		</bndbox>
	</object>
</annotation>
